semantic_synth/__init__.py
semantic_synth/datagen.py
semantic_synth-0.0.3.dist-info/LICENSE
semantic_synth-0.0.3.dist-info/METADATA
semantic_synth-0.0.3.dist-info/WHEEL
semantic_synth-0.0.3.dist-info/top_level.txt
semantic_synth-0.0.3.dist-info/RECORD
