Metadata-Version: 2.1
Name: semantic-synth
Version: 0.0.3
Summary: Synthetic dataset generator for testing semantic search quality
Home-page: https://github.com/wordlabs-io/semantic-synth
Author: Tanishk Kithannae
Author-email: tanishk.kithannae@wordlabs.io
Keywords: python,rag
Classifier: Development Status :: 3 - Alpha
Classifier: Intended Audience :: Developers
Classifier: Programming Language :: Python :: 3
Classifier: Operating System :: MacOS :: MacOS X
Classifier: Operating System :: Microsoft :: Windows
License-File: LICENSE
Requires-Dist: transformers
Requires-Dist: pysbd
Requires-Dist: yake
Requires-Dist: pandas
Requires-Dist: spacy
